manuals/__init__.py
manuals/__main__.py
manuals/formatting.py
manuals/main.py
manuals/manuals.py
manuals/populator.py
manuals/regexp.py
manuals/search.py
manuals/common/__init__.py
manuals/common/click_extension.py
manuals/common/types.py
manuals/err/__init__.py
manuals/err/dev_err.py
manuals/prompt/__init__.py
manuals/prompt/item.py
manuals/prompt/options.py
manuals/prompt/prompt.py
manuals/prompt/util.py
manuals-0.0.19.dist-info/METADATA
manuals-0.0.19.dist-info/WHEEL
manuals-0.0.19.dist-info/top_level.txt
manuals-0.0.19.dist-info/RECORD
