Metadata-Version: 2.1
Name: manuals
Version: 0.0.19
Summary: UNKNOWN
Home-page: https://github.com/giladbarnea/manuals
Author: Gilad Barnea
Author-email: giladbrn@gmail.com
License: MIT
Platform: UNKNOWN
Requires-Python: >=3.8
Requires-Dist: more-termcolor
Requires-Dist: click
Requires-Dist: rich
Requires-Dist: fuzzysearch
Provides-Extra: dev
Requires-Dist: pytest ; extra == 'dev'
Requires-Dist: ipdb ; extra == 'dev'
Requires-Dist: IPython ; extra == 'dev'
Requires-Dist: jupyter ; extra == 'dev'
Requires-Dist: semver ; extra == 'dev'
Requires-Dist: birdseye ; extra == 'dev'
